jwt_auth/__init__.py
jwt_auth/core.py
jwt_auth/exceptions.py
jwt_auth/forms.py
jwt_auth/middleware.py
jwt_auth/mixins.py
jwt_auth/settings.py
jwt_auth/utils.py
jwt_auth/views.py
webstack_django_jwt_auth-1.5.0.dist-info/LICENSE
webstack_django_jwt_auth-1.5.0.dist-info/METADATA
webstack_django_jwt_auth-1.5.0.dist-info/WHEEL
webstack_django_jwt_auth-1.5.0.dist-info/top_level.txt
webstack_django_jwt_auth-1.5.0.dist-info/RECORD
